{
    "reference": {
        "author": [
            "Rajbhandari, B.",
            "Owen, B. J.",
            "Caride, S.",
            "Inta, R."
        ],
        "doi": "10.1103/PhysRevD.104.122008",
        "journal": "Phys. Rev. D",
        "key": "Rajbhandari+2021a",
        "key-suffix": "a",
        "pages": "122008",
        "title": "First searches for gravitational waves from r -modes of the Crab pulsar",
        "volume": "104",
        "year": 2021
    },
    "searches": [
        {
            "algorithm-coherent": "F-statistic",
            "algorithm-incoherent": "none",
            "astro-target": "Crab",
            "breadth": 1575000000.0,
            "category": "pulsar-narrowband",
            "depth": 104.8,
            "max-coherence-time": 11180160.0,
            "obs-run": "O2",
            "param-space": {
                "freq-space-vals": {
                    "Amax": 1.57,
                    "Amin": 1.39,
                    "Bmax": 0.195,
                    "nu": 29.66181,
                    "nuK": 506,
                    "nud": -3.69383e-10,
                    "nudd": 2.41e-20
                },
                "ranges": [
                    {
                        "fddot": [
                            0.0,
                            "nudd * (freq/nu)"
                        ],
                        "fdot": [
                            "nud * ((freq/nu) - 2*Bmax*(nu/nuK)**2)",
                            "nud * (freq/nu)"
                        ],
                        "freq": [
                            41.21,
                            46.569
                        ]
                    }
                ]
            },
            "time-span": 11180160.0
        },
        {
            "algorithm-coherent": "F-statistic",
            "algorithm-incoherent": "none",
            "astro-target": "Crab",
            "breadth": 1571000000.0,
            "category": "pulsar-narrowband",
            "depth": 93.29,
            "max-coherence-time": 11180160.0,
            "obs-run": "O2",
            "param-space": {
                "freq-space-vals": {
                    "Amax": 1.57,
                    "Amin": 1.39,
                    "Bmax": 0.195,
                    "nu": 29.64761,
                    "nuK": 506,
                    "nud": -3.689673e-10,
                    "nudd": 1.92e-20
                },
                "ranges": [
                    {
                        "fddot": [
                            0.0,
                            "nudd * (freq/nu)"
                        ],
                        "fdot": [
                            "nud * ((freq/nu) - 2*Bmax*(nu/nuK)**2)",
                            "nud * (freq/nu)"
                        ],
                        "freq": [
                            41.1903,
                            46.5467
                        ]
                    }
                ]
            },
            "time-span": 11180160.0
        },
        {
            "algorithm-coherent": "F-statistic",
            "algorithm-incoherent": "none",
            "astro-target": "Crab",
            "breadth": 4038000000.0,
            "category": "pulsar-narrowband",
            "depth": 106.7,
            "max-coherence-time": 13037760.0,
            "obs-run": "O2",
            "param-space": {
                "freq-space-vals": {
                    "Amax": 1.57,
                    "Amin": 1.39,
                    "Bmax": 0.195,
                    "nu": 29.6438,
                    "nuK": 506,
                    "nud": -3.688438e-10,
                    "nudd": 2.5e-20
                },
                "ranges": [
                    {
                        "fddot": [
                            0.0,
                            "nudd * (freq/nu)"
                        ],
                        "fdot": [
                            "nud * ((freq/nu) - 2*Bmax*(nu/nuK)**2)",
                            "nud * (freq/nu)"
                        ],
                        "freq": [
                            41.185,
                            46.5408
                        ]
                    }
                ]
            },
            "time-span": 13037760.0
        }
    ]
}
